bsrp/__init__.py
bsrp/client.py
bsrp/constants.py
bsrp/server.py
bsrp/utils.py
bsrp-1.0.1.dist-info/METADATA
bsrp-1.0.1.dist-info/WHEEL
bsrp-1.0.1.dist-info/top_level.txt
bsrp-1.0.1.dist-info/RECORD
