Metadata-Version: 2.1
Name: bsrp
Version: 1.0.1
Summary: B-first SRP-6a protocol implementation
Home-page: https://github.com/abehoffman/bsrp
Author: Abe Hoffman
Author-email: abehoffman@me.com
License: MIT
Platform: UNKNOWN
Classifier: Programming Language :: Python :: 3
Classifier: License :: OSI Approved :: MIT License
Classifier: Operating System :: OS Independent
Classifier: Topic :: Security
Requires-Python: >=3.5
